antiwebx/__init__.py
antiwebx/controller.py
antiwebx/installer.py
antiwebx-0.1.9.dist-info/METADATA
antiwebx-0.1.9.dist-info/WHEEL
antiwebx-0.1.9.dist-info/top_level.txt
antiwebx-0.1.9.dist-info/RECORD
