Metadata-Version: 2.4
Name: antiwebx
Version: 0.1.9
Summary: Run headless Chrome via Selenium on Termux/Pydroid
Author: AntifiedNull
Classifier: Programming Language :: Python :: 3
Classifier: Operating System :: POSIX :: Linux
Requires-Python: >=3.6
Requires-Dist: selenium>=4.0.0
Dynamic: author
Dynamic: classifier
Dynamic: description
Dynamic: description-content-type
Dynamic: requires-dist
Dynamic: requires-python
Dynamic: summary
